serverish/__init__.py
serverish/base/__init__.py
serverish/base/asyncio_util_functions.py
serverish/base/collector.py
serverish/base/datetime.py
serverish/base/exceptions.py
serverish/base/fifoset.py
serverish/base/hasstatuses.py
serverish/base/idmanger.py
serverish/base/iterators.py
serverish/base/manageable.py
serverish/base/singleton.py
serverish/base/status.py
serverish/base/task_manager.py
serverish/connection/__init__.py
serverish/connection/connection.py
serverish/connection/connection_jets.py
serverish/connection/connection_nats.py
serverish/messenger/__init__.py
serverish/messenger/live_document.py
serverish/messenger/logging.py
serverish/messenger/messenger.py
serverish/messenger/msg_callback_sub.py
serverish/messenger/msg_document_read.py
serverish/messenger/msg_journal_pub.py
serverish/messenger/msg_journal_read.py
serverish/messenger/msg_progress_pub.py
serverish/messenger/msg_progress_read.py
serverish/messenger/msg_publisher.py
serverish/messenger/msg_reader.py
serverish/messenger/msg_rpc_req.py
serverish/messenger/msg_rpc_resp.py
serverish/messenger/msg_single_pub.py
serverish/messenger/msg_single_read.py
serverish/messenger/msgvalidator.py
serverish/schema/config.schema.json
serverish/schema/default.schema.json
serverish/schema/include/timestamp.schema.json
serverish/schema/journal.schema.json
serverish/schema/meta.schema.json
serverish/schema/program_current_state.schema.json
serverish/schema/program_state.schema.json
serverish/schema/progress.schema.json
serverish/schema/telemetry.schema.json
serverish/services/TODO.txt
serverish/slog.py
serverish-1.5.1.dist-info/LICENSE
serverish-1.5.1.dist-info/METADATA
serverish-1.5.1.dist-info/WHEEL
serverish-1.5.1.dist-info/RECORD
