Metadata-Version: 2.1
Name: serverish
Version: 1.5.1
Summary: helpers for server alike projects
Home-page: https://github.com/AkondLab/serverish
Author: Mikołaj Kałuszyński
Requires-Python: >=3.10,<4.0
Classifier: Programming Language :: Python :: 3
Classifier: Programming Language :: Python :: 3.10
Classifier: Programming Language :: Python :: 3.11
Classifier: Programming Language :: Python :: 3.12
Provides-Extra: dns
Provides-Extra: messenger
Requires-Dist: aiodns (>=3.2.0,<4.0.0) ; extra == "dns"
Requires-Dist: jsonschema (>=4.20.0,<5.0.0)
Requires-Dist: nats-py (>=2.7.2,<3.0.0) ; extra == "messenger"
Requires-Dist: param (>=2.1.0,<3.0.0)
Project-URL: Repository, https://github.com/AkondLab/serverish
